{
    "post_id": "3867710394606118240",
    "post_shortcode": "DWs3hyklWVg",
    "likes": 1671,
    "liked": false,
    "pinned": [],
    "description": "Суббота день ничего не делания, так вот вам интерьер спальни, где нужно проводить субботние выходные, согласны со мной?!\n4 ракурса дизайн проекта спальни, а на последнем ракурсе дизайн проект гардеробной, тоже оцените 👌👌\n\nВ сторис сегодня поделился отзывами с прошедшего у меня курса, порадуйтесь за дизайнеров!\nАвтор проекта @nuova_home",
    "location_id": "5399624",
    "location_slug": "lamborghini-westlake",
    "location_url": "https://www.instagram.com/explore/locations/5399624/lamborghini-westlake/",
    "sidecar_media_id": "3867710394606118240",
    "sidecar_shortcode": "DWs3hyklWVg",
    "owner_id": "2462019344",
    "username": "berg.interior",
    "fullname": "Design Interior | Worldwide marketing agency",
    "post_date": "2026-04-04 07:17:10",
    "date": "2026-04-04 07:17:09",
    "type": "post",
    "post_url": "https://www.instagram.com/p/DWs3hyklWVg/",
    "count": 4,
    "category": "instagram",
    "subcategory": "post",
    "num": 2,
    "media_id": "3867709167830439830",
    "shortcode": "DWs3P8DDheW",
    "display_url": "https://instagram.fmaa3-3.fna.fbcdn.net/v/t51.82787-15/658237432_18386676343083345_5997028250518614780_n.jpg?stp=dst-jpg_e35_tt6&_nc_cat=109&ig_cache_key=Mzg2NzcwOTE2NzgzMDQzOTgzMA%3D%3D.3-ccb7-5&ccb=7-5&_nc_sid=58cdad&efg=eyJ2ZW5jb2RlX3RhZyI6InhwaWRzLjEwODB4MTI0NC5zZHIuQzMifQ%3D%3D&_nc_ohc=SBTjzRxXAhkQ7kNvwHw53Xb&_nc_oc=AdqbLKx05ctezAz5tGA_2V49ALY9V59is-2cTXgJq5INFEii-OsmNE4lUhBXIzQH5bkrobiFThDSPbI2NfNukvWD&_nc_ad=z-m&_nc_cid=0&_nc_zt=23&_nc_ht=instagram.fmaa3-3.fna&_nc_gid=4G8ZuktWxLeEXp2hTMsDbQ&_nc_ss=7a32e&oh=00_Af30ZwrpPBSkQkx1op0s-tpAZbA7e6XTssVCOYGFT3AD3A&oe=69EA8D67",
    "video_url": null,
    "width": 1080,
    "width_original": 1080,
    "height": 1244,
    "height_original": 1244,
    "tagged_users": [],
    "filename": "658237432_18386676343083345_5997028250518614780_n",
    "extension": "jpg"
}
